word_prediction/__init__.py
word_prediction/predictor.py
sparv_word_prediction_plugin-0.3.0.dist-info/METADATA
sparv_word_prediction_plugin-0.3.0.dist-info/WHEEL
sparv_word_prediction_plugin-0.3.0.dist-info/entry_points.txt
sparv_word_prediction_plugin-0.3.0.dist-info/licenses/LICENSE
sparv_word_prediction_plugin-0.3.0.dist-info/RECORD
