Metadata-Version: 2.1
Name: sparv-word-prediction-plugin
Version: 0.3.0
Summary: A sparv plugin for computing word neighbours using a BERT model.
Project-URL: Homepage, https://github.com/spraakbanken/sparv-word-prediction-plugin
Project-URL: Repository, https://github.com/spraakbanken/sparv-word-prediction-plugin
Project-URL: Bug Tracker, https://github.com/spraakbanken/sparv-word-prediction-plugin/issues
Author-email: Kristoffer Andersson <kristoffer.andersson@gu.se>
License-Expression: MIT
License-File: LICENSE
Classifier: Development Status :: 4 - Beta
Classifier: Intended Audience :: Developers
Classifier: License :: OSI Approved :: MIT License
Classifier: Operating System :: POSIX
Classifier: Operating System :: Unix
Classifier: Programming Language :: Python :: Implementation :: CPython
Classifier: Topic :: Utilities
Requires-Python: >=3.9
Requires-Dist: sparv-pipeline>=5.2.0
Requires-Dist: tabulate>=0.9.0
Requires-Dist: transformers>=4.34.1
